[{"confidence": "0.3460", "file_id": "77", "bbox": "0 188 375 349"}, {"confidence": "0.2527", "file_id": "84", "bbox": "61 101 358 312"}, {"confidence": "0.1383", "file_id": "100", "bbox": "169 166 271 255"}, {"confidence": "0.0802", "file_id": "54", "bbox": "63 204 367 385"}, {"confidence": "0.0728", "file_id": "36", "bbox": "17 266 274 415"}, {"confidence": "0.0708", "file_id": "104", "bbox": "0 200 415 411"}, {"confidence": "0.0580", "file_id": "104", "bbox": "160 277 294 388"}, {"confidence": "0.0579", "file_id": "23", "bbox": "143 154 214 310"}, {"confidence": "0.0570", "file_id": "44", "bbox": "126 125 190 222"}, {"confidence": "0.0567", "file_id": "0", "bbox": "218 155 344 274"}]